[
  {
    "id": 15,
    "nickname": "토마토러버전종우",
    "categoryName": "도배",
    "description": "Hello, World!",
    "status": "미완료"
  },
  {
    "id": 14,
    "nickname": "토마토러버전종우",
    "categoryName": "도배",
    "description": "Hello, World!",
    "status": "미완료"
  },
  {
    "id": 13,
    "nickname": "토마토러버전종우",
    "categoryName": "도배",
    "description": "Hello, World!",
    "status": "미완료"
  },
  {
    "id": 12,
    "nickname": "토마토러버전종우",
    "categoryName": "도배",
    "description": "Hello, World!",
    "status": "미완료"
  },
  {
    "id": 11,
    "nickname": "토마토러버전종우",
    "categoryName": "도배",
    "description": "Hello, World!",
    "status": "미완료"
  },
  {
    "id": 10,
    "nickname": "토마토러버전종우",
    "categoryName": "도배",
    "description": "Hello, World!",
    "status": "미완료"
  },
  {
    "id": 9,
    "nickname": "토마토러버전종우",
    "categoryName": "욕설",
    "description": "Hello, World!",
    "status": "미완료"
  },
  {
    "id": 8,
    "nickname": "토마토러버전종우",
    "categoryName": "도배",
    "description": "Hello, World!",
    "status": "미완료"
  },
  {
    "id": 7,
    "nickname": "토마토러버전종우",
    "categoryName": "욕설",
    "description": "Hello, World!",
    "status": "미완료"
  },
  {
    "id": 6,
    "nickname": "토마토러버전종우",
    "categoryName": "도배",
    "description": "Hello, World!",
    "status": "미완료"
  },
  {
    "id": 5,
    "nickname": "토마토러버전종우",
    "categoryName": "욕설",
    "description": "Hello, World!",
    "status": "미완료"
  },
  {
    "id": 4,
    "nickname": "토마토러버전종우",
    "categoryName": "욕설",
    "description": "abcskdskl232323op2i323kl2mdklmns 3451325641 235413 2654123564 123564135264 13526413256 41235641563 21",
    "status": "미완료"
  },
  {
    "id": 3,
    "nickname": "바나나러버신성우",
    "categoryName": "욕설",
    "description": "토마토맛토마톳마톳마토타모타",
    "status": "미완료"
  },
  {
    "id": 2,
    "nickname": "사과러버윤서희",
    "categoryName": "도배",
    "description": "21515648123",
    "status": "처리 완료"
  },
  {
    "id": 1,
    "nickname": "토마토러버전종우",
    "categoryName": "욕설",
    "description": "가나다라맙소사",
    "status": "처리 완료"
  }
]
